ebuffer/__init__.py
ebuffer/apiebuffer.py
ebuffer/apiuserobj.py
ebuffer/application.py
ebuffer/config.py
ebuffer/errors.py
ebuffer/models_buffer.py
ebuffer/models_common.py
ebuffer/auth/__init__.py
ebuffer/auth/auth.py
ebuffer/auth/openid.py
ebuffer/auth/passfile.py
ebuffer/backends/__init__.py
ebuffer/backends/acl.py
ebuffer/backends/backends.py
ebuffer/backends/memory.py
ebuffer/backends/mmap.py
ebuffer/database/__init__.py
ebuffer/database/cruduser.py
ebuffer/database/cruduserobj.py
ebuffer/database/database.py
ebuffer/database/privmodel_buffer.py
ebuffer/database/privmodel_user.py
ebuffer/database/privmodel_userobj.py
ebuffer/routers/__init__.py
ebuffer/routers/routes_auth.py
ebuffer/routers/routes_buffer.py
ebuffer/server/__init__.py
ebuffer/server/main.py
ebuffer-0.1.5.dist-info/licenses/LICENSE
ebuffer-0.1.5.dist-info/METADATA
ebuffer-0.1.5.dist-info/WHEEL
ebuffer-0.1.5.dist-info/top_level.txt
ebuffer-0.1.5.dist-info/RECORD
