Metadata-Version: 2.4
Name: ebuffer
Version: 0.1.5
Summary: Ephemeral buffer service
Author-email: Laurent Morin <Laurent.Morin@irisa.fr>, Yawa Germaine Nyatsikor <yawa-germaine.nyatsikor@irisa.fr>
License-Expression: MIT
Project-URL: Homepage, https://ebuffer.aqmo.org/
Project-URL: Documentation, https://ebuffer.aqmo.org/
Project-URL: Repository, https://ebuffer.aqmo.org/
Project-URL: Issues, https://ebuffer.aqmo.org/
Project-URL: Changelog, https://ebuffer.aqmo.org/
Keywords: HPC,buffers,workflow,distributed
Classifier: Programming Language :: Python :: 3.10
Classifier: Programming Language :: Python :: 3.12
Classifier: Operating System :: OS Independent
Classifier: Topic :: Scientific/Engineering
Classifier: Topic :: System :: Benchmark
Classifier: Topic :: System :: Distributed Computing
Requires-Python: >=3.10
License-File: LICENSE
Requires-Dist: fastapi>=0.115.8
Requires-Dist: pydantic>=2.10.6
Requires-Dist: Requests>=2.32.3
Requires-Dist: SQLAlchemy>=2.0.38
Requires-Dist: sqlmodel>=0.0.22
Provides-Extra: all
Provides-Extra: docs
Provides-Extra: dev
Dynamic: license-file
